bangla_linga/BN_countvectorizer.py
bangla_linga/BN_ngram.py
bangla_linga/__init__.py
bangla_linga/gender_prediction.py
bangla_linga/iden.yaml
bangla_linga/name_gen_model
bangla_linga/word_set
bangla_linga-0.4.dist-info/LICENSE
bangla_linga-0.4.dist-info/METADATA
bangla_linga-0.4.dist-info/WHEEL
bangla_linga-0.4.dist-info/top_level.txt
bangla_linga-0.4.dist-info/RECORD
