Metadata-Version: 2.1
Name: bangla-linga
Version: 0.4
Summary: UNKNOWN
Home-page: https://github.com/Kowsher/Bangla-NLP/tree/master/Bangla%20Linga
Author: Kowsher Ahmed
Author-email: 
License: MIT
Platform: UNKNOWN
Classifier: Programming Language :: Python :: 3
Classifier: License :: OSI Approved :: MIT License
Classifier: Operating System :: OS Independent
